oscan/__init__.py
oscan/__main__.py
oscan/dto/__init__.py
oscan/error/__init__.py
oscan/util/__init__.py
tests/__init__.py
oscan-0.0.5.dist-info/LICENSE
oscan-0.0.5.dist-info/METADATA
oscan-0.0.5.dist-info/WHEEL
oscan-0.0.5.dist-info/entry_points.txt
oscan-0.0.5.dist-info/top_level.txt
oscan-0.0.5.dist-info/RECORD
