Metadata-Version: 2.1
Name: oscan
Version: 0.0.5
Summary: Scanner used to build Pyrustic Backstage
Home-page: https://github.com/pyrustic/oscan
Author: Pyrustic Evangelist
Author-email: rusticalex@yahoo.com
Maintainer: Pyrustic Evangelist
Maintainer-email: rusticalex@yahoo.com
License: MIT
Keywords: scan,scanner,regex,regular-expression,text,pyrustic
Platform: UNKNOWN
Classifier: Programming Language :: Python :: 3
Classifier: License :: OSI Approved :: MIT License
Classifier: Operating System :: OS Independent
Requires-Python: >=3.5
License-File: LICENSE
